py_models/__init__.py
py_models/graph_tree_rooted.py
py_models/interval.py
py_models_by_sporniket-1.0.0.dist-info/METADATA
py_models_by_sporniket-1.0.0.dist-info/WHEEL
py_models_by_sporniket-1.0.0.dist-info/entry_points.txt
py_models_by_sporniket-1.0.0.dist-info/licenses/LICENCE
py_models_by_sporniket-1.0.0.dist-info/RECORD
