Metadata-Version: 2.1
Name: py-models-by-sporniket
Version: 1.0.0
Summary: A collection of basic data models in python
Keywords: python,data models,interval,rooted tree
Author-Email: Sporniket <sporniket.studio@gmail.com>
License: GPL-3.0-or-later
Project-URL: homepage, https://github.com/sporniket/py-models
Project-URL: repository, https://github.com/sporniket/py-models
Project-URL: bug-tracker, https://github.com/sporniket/py-models/issues
Requires-Python: >=3.9
